sourced_ml_core-0.0.6-py3.6-nspkg.pth
sourced/ml/core/__init__.py
sourced/ml/core/modelforgecfg.py
sourced/ml/core/algorithms/__init__.py
sourced/ml/core/algorithms/id_embedding.py
sourced/ml/core/algorithms/swivel.py
sourced/ml/core/algorithms/tf_idf.py
sourced/ml/core/algorithms/token_parser.py
sourced/ml/core/algorithms/uast_id_distance.py
sourced/ml/core/algorithms/uast_ids_to_bag.py
sourced/ml/core/algorithms/uast_inttypes_to_graphlets.py
sourced/ml/core/algorithms/uast_inttypes_to_nodes.py
sourced/ml/core/algorithms/uast_struct_to_bag.py
sourced/ml/core/algorithms/uast_to_bag.py
sourced/ml/core/algorithms/uast_to_id_sequence.py
sourced/ml/core/algorithms/uast_to_role_id_pairs.py
sourced/ml/core/algorithms/id_splitter/README.md
sourced/ml/core/algorithms/id_splitter/__init__.py
sourced/ml/core/algorithms/id_splitter/features.py
sourced/ml/core/algorithms/id_splitter/nn_model.py
sourced/ml/core/algorithms/id_splitter/pipeline.py
sourced/ml/core/extractors/__init__.py
sourced/ml/core/extractors/bags_extractor.py
sourced/ml/core/extractors/children.py
sourced/ml/core/extractors/graphlets.py
sourced/ml/core/extractors/helpers.py
sourced/ml/core/extractors/id_sequence.py
sourced/ml/core/extractors/identifier_distance.py
sourced/ml/core/extractors/identifiers.py
sourced/ml/core/extractors/literals.py
sourced/ml/core/extractors/uast_random_walk.py
sourced/ml/core/extractors/uast_seq.py
sourced/ml/core/models/__init__.py
sourced/ml/core/models/bow.py
sourced/ml/core/models/coocc.py
sourced/ml/core/models/df.py
sourced/ml/core/models/id2vec.py
sourced/ml/core/models/id_splitter.py
sourced/ml/core/models/license.py
sourced/ml/core/models/ordered_df.py
sourced/ml/core/models/quant.py
sourced/ml/core/models/tensorflow.py
sourced/ml/core/models/topics.py
sourced/ml/core/models/model_converters/__init__.py
sourced/ml/core/models/model_converters/base.py
sourced/ml/core/models/model_converters/merge_bow.py
sourced/ml/core/models/model_converters/merge_df.py
sourced_ml_core-0.0.6.dist-info/LICENSE.md
sourced_ml_core-0.0.6.dist-info/METADATA
sourced_ml_core-0.0.6.dist-info/WHEEL
sourced_ml_core-0.0.6.dist-info/namespace_packages.txt
sourced_ml_core-0.0.6.dist-info/top_level.txt
sourced_ml_core-0.0.6.dist-info/RECORD
