Metadata-Version: 2.1
Name: sourced-ml-core
Version: 0.0.6
Summary: Library containing the core algorithms for machine learning on source code. Provides API and tools to train and use models based on source code features extracted from Babelfish's UASTs.
Home-page: https://github.com/src-d/ml-core
Author: source{d}
Author-email: machine-learning@sourced.tech
License: Apache 2.0
Download-URL: https://github.com/src-d/ml-core
Keywords: machine learning on source code,word2vec,id2vec,github,swivel,bow,bblfsh,babelfish
Platform: UNKNOWN
Classifier: Development Status :: 3 - Alpha
Classifier: Environment :: Console
Classifier: Intended Audience :: Developers
Classifier: License :: OSI Approved :: Apache Software License
Classifier: Operating System :: POSIX
Classifier: Programming Language :: Python :: 3.5
Classifier: Programming Language :: Python :: 3.6
Classifier: Programming Language :: Python :: 3.7
Classifier: Topic :: Software Development :: Libraries
Requires-Python: >=3.5
Requires-Dist: PyStemmer (<2.0,>=1.3)
Requires-Dist: bblfsh (<5.0,>=3.1.0)
Requires-Dist: modelforge (>=0.15.0)
Requires-Dist: pygments (<3.0,>=2.2.0)
Requires-Dist: keras (<3.0,>=2.0)
Requires-Dist: scikit-learn (<1.0,>=0.21.1)
Requires-Dist: tqdm (<5.0,>=4.20)
Provides-Extra: tf
Requires-Dist: tensorflow (<1.14,>=1.0) ; extra == 'tf'
Provides-Extra: tf_gpu
Requires-Dist: tensorflow-gpu (<1.14,>=1.0) ; extra == 'tf_gpu'
